SESAMI/__init__.py
SESAMI/bet.py
SESAMI/lasso_model.sav
SESAMI/mplstyle.txt
SESAMI/predict.py
SESAMI/run.py
SESAMI-2.7.dist-info/LICENSE
SESAMI-2.7.dist-info/METADATA
SESAMI-2.7.dist-info/WHEEL
SESAMI-2.7.dist-info/top_level.txt
SESAMI-2.7.dist-info/RECORD
