Metadata-Version: 2.1
Name: SESAMI
Version: 2.7
Summary: Characterization Tools for Porous Materials Using Nitrogen/Argon Adsorption
Home-page: https://github.com/hjkgrp/SESAMI_web/
Author: Guobin Zhao
Author-email: sxmzhaogb@gmai.com
License: MIT
Platform: UNKNOWN
Classifier: Programming Language :: Python :: 3
Classifier: License :: OSI Approved :: MIT License
License-File: LICENSE
Requires-Dist: flask
Requires-Dist: matplotlib
Requires-Dist: numpy
Requires-Dist: pandas
Requires-Dist: pymongo[srv] (==4.1.1)
Requires-Dist: scikit-learn
Requires-Dist: scipy
Requires-Dist: statsmodels
